Metadata-Version: 2.4
Name: xandai-cli
Version: 2.1.9
Summary: XandAI - Multi-Provider AI Terminal Assistant with Interactive Code Execution
Home-page: https://github.com/XandAI-project/Xandai-CLI
Author: XandAI-project
Author-email: XandNet Team <support@xandnet.ai>
License: MIT
Project-URL: Homepage, https://github.com/xandnet/xandai-cli
Project-URL: Repository, https://github.com/xandnet/xandai-cli
Project-URL: Issues, https://github.com/xandnet/xandai-cli/issues
Keywords: ai,cli,ollama,lm-studio,assistant,terminal
Classifier: Development Status :: 4 - Beta
Classifier: Intended Audience :: Developers
Classifier: Topic :: Software Development :: Libraries :: Python Modules
Classifier: License :: OSI Approved :: MIT License
Classifier: Programming Language :: Python :: 3
Classifier: Programming Language :: Python :: 3.8
Classifier: Programming Language :: Python :: 3.9
Classifier: Programming Language :: Python :: 3.10
Classifier: Programming Language :: Python :: 3.11
Requires-Python: >=3.8
License-File: LICENSE
Requires-Dist: requests>=2.31.0
Requires-Dist: prompt-toolkit>=3.0.47
Requires-Dist: rich>=13.0.0
Requires-Dist: colorama>=0.4.6
Requires-Dist: pydantic>=2.0.0
Provides-Extra: dev
Requires-Dist: pytest>=7.0.0; extra == "dev"
Requires-Dist: pytest-cov>=4.0.0; extra == "dev"
Requires-Dist: black>=23.0.0; extra == "dev"
Requires-Dist: isort>=5.12.0; extra == "dev"
Requires-Dist: flake8>=6.0.0; extra == "dev"
Requires-Dist: mypy>=1.0.0; extra == "dev"
Requires-Dist: pre-commit>=3.0.0; extra == "dev"
Dynamic: author
Dynamic: home-page
Dynamic: license-file
Dynamic: requires-python
